AviListPy/__init__.py
AviListPy/data/__init__.py
AviListPy/data/avilistdatabase.py
AviListPy/taxonomy/__init__.py
AviListPy/taxonomy/family.py
AviListPy/taxonomy/genus.py
AviListPy/taxonomy/order.py
AviListPy/taxonomy/species.py
AviListPy/taxonomy/subspecies.py
avilistpy-1.0.6.dist-info/licenses/LICENSE
avilistpy-1.0.6.dist-info/METADATA
avilistpy-1.0.6.dist-info/WHEEL
avilistpy-1.0.6.dist-info/top_level.txt
avilistpy-1.0.6.dist-info/RECORD
