Metadata-Version: 2.4
Name: AviListPy
Version: 1.0.6
Summary: Python implementation of the 2025 AviList Global Avian Checklist.
Author-email: Thomas Lee <tl165@rice.edu>
Maintainer-email: Thomas Lee <tl165@rice.edu>
License-Expression: CC0-1.0
Project-URL: Homepage, https://github.com/geothomaslee/AviListPy/
Project-URL: Issues, https://github.com/geothomaslee/AviListPy/issues
Classifier: Programming Language :: Python :: 3
Classifier: Programming Language :: Python :: 3.10
Classifier: Programming Language :: Python :: 3.11
Classifier: Programming Language :: Python :: 3.12
Classifier: Programming Language :: Python :: 3.13
Classifier: Operating System :: OS Independent
Requires-Python: >=3.10
License-File: LICENSE
Requires-Dist: pandas>=2.3.0
Requires-Dist: openpyxl>=3.1.5
Dynamic: license-file
